setup.py
pyjojo/__init__.py
pyjojo/config.py
pyjojo/handlers.py
pyjojo/options.py
pyjojo/scripts.py
pyjojo/server.py
pyjojo/servers.py
pyjojo/util.py
pyjojo.egg-info/PKG-INFO
pyjojo.egg-info/SOURCES.txt
pyjojo.egg-info/dependency_links.txt
pyjojo.egg-info/entry_points.txt
pyjojo.egg-info/not-zip-safe
pyjojo.egg-info/requires.txt
pyjojo.egg-info/top_level.txt