Metadata-Version: 1.0
Name: pyjojo
Version: 0.8
Summary: Expose a set of shell scripts as an API.
Home-page: https://github.com/atarola/pyjojo
Author: Anthony Tarola
Author-email: anthony.tarola@gmail.com
License: UNKNOWN
Platform: UNKNOWN
